torch_geometric_temporal/__init__.py
torch_geometric_temporal/dataset/__init__.py
torch_geometric_temporal/dataset/chickenpox.py
torch_geometric_temporal/dataset/download.py
torch_geometric_temporal/dataset/encovid.py
torch_geometric_temporal/dataset/metr_la.py
torch_geometric_temporal/dataset/montevideo_bus.py
torch_geometric_temporal/dataset/mtm.py
torch_geometric_temporal/dataset/pedalme.py
torch_geometric_temporal/dataset/pems.py
torch_geometric_temporal/dataset/pemsAllLA.py
torch_geometric_temporal/dataset/pems_bay.py
torch_geometric_temporal/dataset/twitter_tennis.py
torch_geometric_temporal/dataset/wikimath.py
torch_geometric_temporal/dataset/windmilllarge.py
torch_geometric_temporal/dataset/windmillmedium.py
torch_geometric_temporal/dataset/windmillsmall.py
torch_geometric_temporal/nn/__init__.py
torch_geometric_temporal/nn/attention/__init__.py
torch_geometric_temporal/nn/attention/astgcn.py
torch_geometric_temporal/nn/attention/dnntsp.py
torch_geometric_temporal/nn/attention/gman.py
torch_geometric_temporal/nn/attention/mstgcn.py
torch_geometric_temporal/nn/attention/mtgnn.py
torch_geometric_temporal/nn/attention/stgcn.py
torch_geometric_temporal/nn/attention/tsagcn.py
torch_geometric_temporal/nn/hetero/__init__.py
torch_geometric_temporal/nn/hetero/heterogclstm.py
torch_geometric_temporal/nn/recurrent/__init__.py
torch_geometric_temporal/nn/recurrent/agcrn.py
torch_geometric_temporal/nn/recurrent/attentiontemporalgcn.py
torch_geometric_temporal/nn/recurrent/dcrnn.py
torch_geometric_temporal/nn/recurrent/dygrae.py
torch_geometric_temporal/nn/recurrent/evolvegcnh.py
torch_geometric_temporal/nn/recurrent/evolvegcno.py
torch_geometric_temporal/nn/recurrent/gc_lstm.py
torch_geometric_temporal/nn/recurrent/gconv_gru.py
torch_geometric_temporal/nn/recurrent/gconv_lstm.py
torch_geometric_temporal/nn/recurrent/lrgcn.py
torch_geometric_temporal/nn/recurrent/mpnn_lstm.py
torch_geometric_temporal/nn/recurrent/temporalgcn.py
torch_geometric_temporal-0.56.2.dist-info/LICENSE
torch_geometric_temporal-0.56.2.dist-info/METADATA
torch_geometric_temporal-0.56.2.dist-info/WHEEL
torch_geometric_temporal-0.56.2.dist-info/top_level.txt
torch_geometric_temporal-0.56.2.dist-info/RECORD
