Metadata-Version: 2.1
Name: torch_geometric_temporal
Version: 0.56.2
Summary: A Temporal Extension Library for PyTorch Geometric.
Home-page: https://github.com/benedekrozemberczki/pytorch_geometric_temporal
Download-URL: https://github.com/benedekrozemberczki/pytorch_geometric_temporal/archive/v0.54.0.tar.gz
Author: Benedek Rozemberczki
Author-email: benedek.rozemberczki@gmail.com
License: MIT
Keywords: machine-learning,deep-learning,deeplearning,deep learning,machine learning,signal processing,temporal signal,graph,dynamic graph,embedding,dynamic embedding,graph convolution,gcn,graph neural network,graph attention,lstm,temporal network,representation learning,learning
Classifier: Development Status :: 3 - Alpha
Classifier: Intended Audience :: Developers
Classifier: Topic :: Software Development :: Build Tools
Classifier: License :: OSI Approved :: MIT License
Classifier: Programming Language :: Python :: 3.6
Requires-Python: >=3.6
License-File: LICENSE
Requires-Dist: decorator ==4.4.2
Requires-Dist: torch
Requires-Dist: cython
Requires-Dist: torch-sparse
Requires-Dist: torch-scatter
Requires-Dist: torch-geometric
Requires-Dist: numpy
Requires-Dist: networkx
Provides-Extra: ddp
Requires-Dist: dask[distributed] ; extra == 'ddp'
Requires-Dist: dask-pytorch-ddp ; extra == 'ddp'
Requires-Dist: pandas ; extra == 'ddp'
Requires-Dist: tables ; extra == 'ddp'
Provides-Extra: index
Requires-Dist: dask ; extra == 'index'
Requires-Dist: pandas ; extra == 'index'
Requires-Dist: tables ; extra == 'index'
Provides-Extra: test
Requires-Dist: pytest ; extra == 'test'
Requires-Dist: pytest-cov ; extra == 'test'
Requires-Dist: mock ; extra == 'test'
Requires-Dist: networkx ; extra == 'test'
Requires-Dist: tqdm ; extra == 'test'
Requires-Dist: dask ; extra == 'test'
Requires-Dist: pandas ; extra == 'test'
Requires-Dist: tables ; extra == 'test'
